openapi_type/__init__.py
openapi_type/custom_types.py
openapi_type/info.py
openapi_type/py.typed
openapi_type/cli/__init__.py
openapi_type/cli/check.py
openapi_type-0.2.0.dist-info/LICENSE.txt
openapi_type-0.2.0.dist-info/METADATA
openapi_type-0.2.0.dist-info/WHEEL
openapi_type-0.2.0.dist-info/entry_points.txt
openapi_type-0.2.0.dist-info/top_level.txt
openapi_type-0.2.0.dist-info/RECORD
