Metadata-Version: 2.1
Name: openapi-type
Version: 0.2.0
Summary: OpenAPI Type
Home-page: https://github.com/avanov/openapi-type
Author: Maxim Avanov
Author-email: maxim.avanov@gmail.com
License: UNKNOWN
Keywords: typing json yaml openapi oas swagger schema serialization deserialization structured-data
Platform: UNKNOWN
Classifier: Intended Audience :: Developers
Classifier: License :: OSI Approved
Classifier: License :: OSI Approved :: MIT License
Classifier: Programming Language :: Python
Classifier: Programming Language :: Python :: 3
Classifier: Operating System :: POSIX
License-File: LICENSE.txt
Requires-Dist: typeit (>=3.10)
Provides-Extra: third_party
Requires-Dist: pyyaml ; extra == 'third_party'
